pybackupper/__init__.py
pybackupper/Google/GAuth.py
pybackupper/Google/GMain.py
pybackupper/Google/GRequests.py
pybackupper/Google/__init__.py
pybackupper/Yandex/YAuth.py
pybackupper/Yandex/YMain.py
pybackupper/Yandex/YRequests.py
pybackupper/Yandex/__init__.py
pybackupper-3.0.dist-info/METADATA
pybackupper-3.0.dist-info/WHEEL
pybackupper-3.0.dist-info/top_level.txt
pybackupper-3.0.dist-info/RECORD
