Metadata-Version: 2.1
Name: pybackupper
Version: 3.0
Summary: Realise files copy on your Cloud Services
Home-page: https://github.com/SavelevMatthew/backupper
Author: Matthew Savelev
Author-email: savelevmatthew@gmail.com
License: MIT
Platform: UNKNOWN
